arkpy.py
ez_setup.py
setup.py
arkpy.egg-info/PKG-INFO
arkpy.egg-info/SOURCES.txt
arkpy.egg-info/dependency_links.txt
arkpy.egg-info/top_level.txt
bin/arkmint
bin/arkvalidate