Metadata-Version: 1.0
Name: arkpy
Version: 0.6
Summary: Simple tools built around the Archival Resource Key
Home-page: http://github.com/mjgiarlo/arkpy
Author: Michael J. Giarlo
Author-email: leftwing@alumni.rutgers.edu
License: UNKNOWN
Platform: UNKNOWN
